{
  "abstract": "Female plot managers in Sub-Saharan Africa often realize significantly lower crop yields than their male counterparts. Even for legumes, which are often referred to as ‘women’s crops’, yields are significantly lower. This study investigated the underlying causes of this gender yield gap in groundnut production. The analysis is based on survey data from 228 farm households from two groundnut growing regions in Uganda. We used the Blinder-Oaxaca model to decompose factors that contribute to this yield gap. Results show 63% and 44% gender yield gaps for improved and local varieties, respectively, with female plot managers realizing less than their male counterparts. Improved groundnut seeds increase female plot manager’s yields but not the yields of male plot managers. Male advantage and female disadvantage combined account for more than 70% of the yield gap in both improved and local groundnut variety production and exceed pure productivity differences. Labor use differences between female and male plot managers and variety types explain the observed yield gap. Interventions and policies that increase women’s access to productive inputs including improved seed will significantly contribute to closing the yield gap, and thereby increase crop production, food security, as well as women’s incomes.",
  "eprint_status": "archive",
  "creators": [
    {
      "gender": null,
      "name": {
        "given": "J",
        "family": "Mugisha",
        "lineage": null,
        "honourific": null
      }
    },
    {
      "gender": null,
      "name": {
        "given": "C",
        "family": "Sebatta",
        "lineage": null,
        "honourific": null
      }
    },
    {
      "gender": null,
      "name": {
        "given": "K",
        "family": "Mausch",
        "lineage": null,
        "honourific": null
      }
    },
    {
      "gender": "Female",
      "name": {
        "given": "E",
        "family": "Ahikiriza",
        "lineage": null,
        "honourific": null
      }
    },
    {
      "gender": null,
      "name": {
        "given": "D",
        "family": "Kalule Okello",
        "lineage": null,
        "honourific": null
      }
    },
    {
      "gender": "Female",
      "name": {
        "given": "E M",
        "family": "Njuguna",
        "lineage": null,
        "honourific": null
      }
    }
  ],
  "full_text_status": "public",
  "date_type": "published",
  "dir": "disk0/00/01/11/49",
  "rev_number": 13,
  "funders": [
    "CGIAR Research Program on Grain Legumes and Dryland Cereals (GLDC)",
    "Bill and Melinda Gates Foundation under the Tropical Legume III (TLIII)"
  ],
  "id_number": "10.1080/09718524.2019.1621597",
  "number": 1,
  "issn": "0971-8524",
  "divisions": [
    "CRPS5"
  ],
  "crps": [
    "CG1"
  ],
  "publication": "Gender, Technology and Development",
  "documents": [
    {
      "content": "published",
      "security": "public",
      "format": "application/pdf",
      "formatdesc": "It is an Open Access article",
      "language": "en",
      "placement": 1,
      "mime_type": "application/pdf",
      "main": "Bridging the gap decomposing sources of gender yield gaps in Uganda groundnut production.pdf",
      "uri": "http://oar.icrisat.org/id/document/53806",
      "docid": 53806,
      "files": [
        {
          "mtime": "2019-07-10 05:24:57",
          "hash": "98e3c6c6b42f0dc7c91441586a130fb8",
          "objectid": 53806,
          "fileid": 172664,
          "datasetid": "document",
          "mime_type": "application/pdf",
          "uri": "http://oar.icrisat.org/id/file/172664",
          "filename": "Bridging the gap decomposing sources of gender yield gaps in Uganda groundnut production.pdf",
          "hash_type": "MD5",
          "filesize": 1751068
        }
      ],
      "pos": 1,
      "eprintid": 11149,
      "rev_number": 2
    }
  ],
  "icrisatcreators": [
    {
      "name": {
        "given": "E M",
        "family": "Njuguna",
        "lineage": null,
        "honourific": null
      }
    }
  ],
  "datestamp": "2019-07-10 05:38:09",
  "lastmod": "2020-01-23 08:38:16",
  "pagerange": "19-35",
  "metadata_visibility": "show",
  "userid": 1305,
  "type": "article",
  "uri": "http://oar.icrisat.org/id/eprint/11149",
  "eprintid": 11149,
  "official_url": "https://doi.org/10.1080/09718524.2019.1621597",
  "subjects": [
    "F12",
    "s1.3",
    "s28",
    "s333",
    "s4004"
  ],
  "related_url": [
    {
      "url": "https://scholar.google.co.in/scholar?hl=en&as_sdt=0%2C5&q=Bridging+the+gap+decomposing+sources+of+gender+yield+gaps+in+Uganda+groundnut+production&btnG=",
      "type": "pub"
    }
  ],
  "refereed": "TRUE",
  "affiliation": [
    "Department of Agribusiness and Natural Resource Economics, Makerere University (Kampala)",
    "World Agroforestry (ICRAF) (Nairobi)",
    "NARO/National Semi-Arid Resources Research Institute (NaSARRI) (Soroti)",
    "ICRISAT (Nairobi)"
  ],
  "country": [
    "Uganda",
    "Kenya"
  ],
  "publisher": "Taylor & Francis",
  "keywords": "Blinder-Oaxaca model, female-managed plot, male-managed plot, gender yield gap, sub-Saharan Africa, groundnut,\r\ngender disparities, groundnut production, project interventions, Uganda, gender differences, groundnut yields, gender equity, food production, women in agriculture, female agriculturists",
  "ispublished": "pub",
  "date": 2019,
  "note": "The authors thank the farmers who volunteered information that enabled this research as well as the anonymous reviewers for providing valuable feedback that significantly improved this work.",
  "volume": 23,
  "title": "Bridging the gap: decomposing sources of gender yield gaps in Uganda groundnut production",
  "status_changed": "2019-07-10 05:38:09"
}