{
  "eprint_id": 11554,
  "title": "Towards bamboo agroforestry development in Ghana: evaluation of crop performance, soil properties and economic benefit",
  "abstract": "In the quest to promote bamboo agroforestry\r\nin the dry semi-deciduous forest zone of\r\nGhana, we evaluated changes in soil properties, crop\r\nproductivity and the economic potential of a bamboobased\r\nintercropping system. The intercropping system\r\nwas established from 3-months old sympodial\r\nbamboo (Bambusa balcooa) seedlings planted at a\r\n5 m95 m spacing and intercropped with maize,\r\ncassava or cowpea. Separate monocropping fields for\r\nmaize, cassava, cowpea and bamboo were set up\r\nadjacent to the intercropped field. In both the\r\nintercropping and monocropping fields, plots were\r\nwith fertilizer treatments and without. The experiment\r\nwas laid out in a split plot design with four\r\nreplicates and studied over three years. Economic\r\nanalysis was conducted using the financial benefit-cost ratio method. The results showed that regardless\r\nof fertilizer treatments, bamboo agroforestry and\r\nmonocropped fields had comparable effects on soil\r\nproperties and crop productivity within two years of\r\nestablishment. In the third year, however, bamboo\r\nagroforestry had significantly (p\\0.05) higher soil\r\nmoisture, pH and crop productivity levels. An\r\nintercropping advantage over monocropping was\r\nevident for all crops with respective partial land\r\nequivalent ratios for fertilized and non-fertilized\r\nintercropped systems as follows: cowpea (1.37 and\r\n1.54), maize (1.38 and 1.36), and cassava (1.12 and\r\n1.19). The economic evaluation also indicated\r\nmarginal profitability of bamboo intercropping over\r\nmonocropping systems. From the results obtained,\r\nthere are clear indications that where bamboo is a\r\nprioritized woody perennial, integrated systems with\r\ncrops may be encouraged.",
  "authors": [
    {
      "given": "D S",
      "family": "Akoto"
    },
    {
      "given": "S T",
      "family": "Partey"
    },
    {
      "given": "M",
      "family": "Denich"
    },
    {
      "given": "M",
      "family": "Kwaku"
    },
    {
      "given": "C",
      "family": "Borgemeister"
    },
    {
      "given": "C B",
      "family": "Schmitt"
    },
    {
      "given": "S T",
      "family": "Partey"
    }
  ],
  "keywords": [
    "Agroecology",
    "Crop productivity",
    "Food security",
    "Soil productivity",
    "Sustainable agriculture"
  ],
  "subjects": [
    "GH1",
    "S25",
    "cr1",
    "s2.11",
    "s2.4",
    "s26"
  ],
  "agrotags": [],
  "fishtags": [],
  "geotags": [],
  "publication": "Agroforestry Systems (TSI)",
  "date": "2020-04",
  "date_type": "published",
  "type": "article",
  "item_type": "article",
  "issn": "0167-4366",
  "doi": "",
  "official_url": "https://doi.org/10.1007/s10457-020-00493-7",
  "uri": "http://oar.icrisat.org/id/eprint/11554",
  "funders": [],
  "pdf_urls": [
    {
      "url": "http://oar.icrisat.org/id/file/178554",
      "filename": "s10457-020-00493-7.pdf",
      "size": 941121,
      "restricted": false
    }
  ],
  "full_text_status": "public",
  "ispublished": "pub"
}