{
  "eprint_id": 12123,
  "title": "Spatially differentiated nitrogen supply is key in a global food–fertilizer price crisis",
  "abstract": "A regional geopolitical conflict and sudden massive supply disruptions have revealed vulnerabilities in our global fuel–fertilizer–food nexus. As nitrogen (N) fertilizer price spikes threaten food security, differentiated responses are required to maintain staple cereal yields across over- and underfertilized agricultural systems. Through integrated management of organic and inorganic N sources in high- to low-input cereal production systems, we estimate potential total N-fertilizer savings of 11% in India, 49% in Ethiopia and 44% in Malawi. Shifting to more cost-effective, high-N fertilizer (such as urea), combined with compost and integration of legumes, can optimize N in N-deficient systems. Better targeted and more efficient N-fertilizer use will benefit systems with surplus N. Geospatially differentiated fertilization strategies should prioritize high-N fertilizer supply to low-yield, N-deficient locations and balanced fertilization of N, P, K and micronutrients in high-yield systems. Nationally, governments can invest in extension and realign subsidies to enable and incentivize improved N management at the farm level.",
  "authors": [
    {
      "given": "S",
      "family": "Snapp"
    },
    {
      "given": "T B",
      "family": "Sapkota"
    },
    {
      "given": "J",
      "family": "Chamberlin"
    },
    {
      "given": "C M",
      "family": "Cox"
    },
    {
      "given": "S",
      "family": "Gameda"
    },
    {
      "given": "M L",
      "family": "Jat"
    },
    {
      "given": "P",
      "family": "Marenya"
    },
    {
      "given": "K A",
      "family": "Mottalebab"
    },
    {
      "given": "C",
      "family": "Negra"
    },
    {
      "given": "K",
      "family": "Senthilkumar"
    },
    {
      "given": "T S",
      "family": "Sida"
    },
    {
      "given": "U",
      "family": "Singh"
    },
    {
      "given": "Z P",
      "family": "Stewart"
    },
    {
      "given": "K",
      "family": "Tesfaye"
    },
    {
      "given": "B",
      "family": "Govaerts"
    },
    {
      "given": "M L",
      "family": "Jat"
    }
  ],
  "keywords": [
    "nitrogen",
    "micronutrients",
    "sub-Saharan Africa",
    "India",
    "Malawi",
    "Ethiopia"
  ],
  "subjects": [
    "S1",
    "s32",
    "s54",
    "s60"
  ],
  "agrotags": [],
  "fishtags": [],
  "geotags": [],
  "publication": "Nature Sustainability",
  "date": "2023-06-29",
  "date_type": "published",
  "type": "article",
  "item_type": "article",
  "issn": "2398-9629",
  "doi": "",
  "official_url": "https://www.nature.com/articles/s41893-023-01166-w",
  "uri": "http://oar.icrisat.org/id/eprint/12123",
  "funders": [],
  "pdf_urls": [
    {
      "url": "http://oar.icrisat.org/id/file/185740",
      "filename": "Nature Sustainability_01-11_2023.pdf",
      "size": 2062679,
      "restricted": false
    }
  ],
  "full_text_status": "public",
  "ispublished": "pub"
}