{
  "publication": "Indian Journal of Agricultural Economics",
  "lastmod": "2011-08-12 06:23:59",
  "title": "Unlocking the Potential of Agriculture in North-eastern Hill Region of India",
  "datestamp": "2011-08-12 06:23:59",
  "icrisatcreators": [
    {
      "name": {
        "given": "P S",
        "family": "Birthal",
        "honourific": null,
        "lineage": null
      }
    }
  ],
  "creators": [
    {
      "name": {
        "given": "P S",
        "family": "Birthal",
        "honourific": null,
        "lineage": null
      }
    }
  ],
  "volume": 65,
  "userid": 14,
  "dir": "disk0/00/00/01/53",
  "pagerange": "329-343",
  "contact_email": "Library-ICRISAT@cgiar.org",
  "ispublished": "pub",
  "eprintid": 153,
  "full_text_status": "public",
  "metadata_visibility": "show",
  "item_issues_count": 0,
  "agrotags": "<b>Agrotags</b>     - NOT-AVAILABLE<br><b>Fishtags</b>    - NOT-AVAILABLE<br><b>Geopoliticaltags</b> - NOT-AVAILABLE",
  "subjects": [
    "s2.4"
  ],
  "status_changed": "2011-08-12 06:23:59",
  "documents": [
    {
      "security": "public",
      "rev_number": 2,
      "docid": 429,
      "language": "en",
      "files": [
        {
          "filename": "new6.pdf",
          "mtime": "2011-08-12 05:55:06",
          "filesize": 758831,
          "hash_type": "MD5",
          "hash": "8d96eea3f0d9fa26bff83faae4fff9b1",
          "datasetid": "document",
          "objectid": 429,
          "uri": "http://oar.icrisat.org/id/file/2492",
          "fileid": 2492,
          "mime_type": "application/pdf"
        }
      ],
      "pos": 1,
      "format": "application/pdf",
      "main": "new6.pdf",
      "eprintid": 153,
      "uri": "http://oar.icrisat.org/id/document/429",
      "placement": 1,
      "mime_type": "application/pdf"
    }
  ],
  "rev_number": 7,
  "related_url": [
    {
      "type": "author",
      "url": "http://scholar.google.co.in/scholar?as_q=Unlocking+the+Potential+of+Agriculture+in+North-eastern+Hill+Region+of+India&num=10&btnG=Search+Scholar&as_epq=&as_oq=&as_eq=&as_occt=title&as_sauthors=&as_publication=&as_ylo=&as_yhi=&as_sdt=1.&as_sdtp=on&as_sdtf="
    }
  ],
  "country": [
    "India"
  ],
  "abstract": "With rich land, abundant water and a favourable climate, hill agriculture in India's north-eastern region, comprising   states like Arunachal Pradesh, Assam, Meghalaya, Manipur, Mizoram, Nagaland, Sikkim and Tripura, has considerable potential to grow, and contribute towards improving farm incomes, enhancing food and nutrition security, reducing rural poverty and accelerating the overall economic growth of the region. Unfortunately the growth potential of hill agriculture has remained under-exploited due to lack of system-specific production technologies, poor infrastructure (transport, markets, processing) and underdeveloped  institutions (credit, extension, information, insurance), notwithstanding the structural constraints imposed by difficult terrains, inaccessible habitations, diverse socio-cultural and agricultural typologies, and small, scattered and fragmented land holdings.",
  "refereed": "TRUE",
  "eprint_status": "archive",
  "type": "article",
  "affiliation": [
    "ICRISAT(Patancheru)"
  ],
  "uri": "http://oar.icrisat.org/id/eprint/153",
  "date": 2010
}