{
  "eprint_id": 388,
  "title": "ICRISAT Annual Report 2004 'Sowing Seeds of Success'",
  "abstract": "It is a novelty and a pleasure to be writing a joint message for ICRISAT’s Annual Report this year, reflecting in no small measure the strong and extremely productive bond between Team ICRISAT and its Governing Board – entities that complement each other so well, that it is difficult to find a definite dividing line.\r\nThe time between the last Annual Report and this one has been profusely encouraging. The Institute has leap-frogged into prominence due to its unique achievements, and has bravely and proudly declared a turnaround for the better.\r\nYou will have seen the following in other documents, but the Governing Board and management recently strengthened it, and it is worth mentioning ICRISAT’s noble guideposts – our vision, mission and mandate.",
  "authors": [
    {
      "given": "-",
      "family": "ICRISAT"
    },
    {
      "given": "-",
      "family": "ICRISAT"
    }
  ],
  "keywords": [
    "Annual Report",
    "ICRISAT Annual Report",
    "ICRISAT"
  ],
  "subjects": [
    "AR1"
  ],
  "agrotags": [],
  "fishtags": [],
  "geotags": [],
  "publication": "",
  "date": 2004,
  "date_type": "published",
  "type": "Annual",
  "item_type": "Annual",
  "issn": "",
  "doi": "",
  "official_url": "",
  "uri": "http://oar.icrisat.org/id/eprint/388",
  "funders": [],
  "pdf_urls": [
    {
      "url": "http://oar.icrisat.org/id/file/4865",
      "filename": "CO_0039.pdf",
      "size": 2511508,
      "restricted": false
    }
  ],
  "full_text_status": "public",
  "ispublished": "pub"
}