{
  "eprint_id": 4018,
  "title": "The Impact of Winter-Sown Chickpeas on Insect Pests and their Management",
  "abstract": "Recent research has shown that in and around Syria, winter-sown chickpea\r\nsubstantially outyields the spring-sown crops. It is expected that there will be a\r\nsubstantial adoption of this practice in farmers' fields in the near future.\r\nAny substantial change in the sowing date of a crop that is already well\r\nestablished in a traditional cropping system can bring about some changes in pest\r\nincidence, not only on that crop but alsoon other crops in the system. Although it\r\nis probable that winter.sown chickpea will suffer no greatcr pest attack than the\r\nspring-sown, it is possible that the introduction of a winter-sown crop might\r\nprovide an earlier buildup of pests that will then disperse lo subsequent $pringsown\r\ncrops including chickpea. Alternatively, a relatively unimporlant insect\r\nmight become important either on the winter or succeeding crop, and so cause\r\nproblems for the farmers.",
  "authors": [
    {
      "given": "S",
      "family": "Sithanantham"
    },
    {
      "given": "O",
      "family": "Tahhan"
    },
    {
      "given": "G",
      "family": "Hariri"
    },
    {
      "given": "W",
      "family": "Reed"
    },
    {
      "given": "S",
      "family": "Sithanantham"
    },
    {
      "given": "W",
      "family": "Reed"
    }
  ],
  "keywords": [],
  "subjects": [
    "s1.1"
  ],
  "agrotags": [],
  "fishtags": [],
  "geotags": [],
  "publication": "",
  "date": 1981,
  "date_type": "",
  "type": "conference_item",
  "item_type": "conference_item",
  "issn": "",
  "doi": "",
  "official_url": "",
  "uri": "http://oar.icrisat.org/id/eprint/4018",
  "funders": [],
  "pdf_urls": [
    {
      "url": "http://oar.icrisat.org/id/file/50067",
      "filename": "CP_035.pdf",
      "size": 1098278,
      "restricted": false
    }
  ],
  "full_text_status": "public",
  "ispublished": "pub"
}