{
  "type": "article",
  "volume": 5,
  "userid": 14,
  "ispublished": "pub",
  "uri": "http://oar.icrisat.org/id/eprint/421",
  "datestamp": "2011-08-25 08:11:24",
  "affiliation": [
    "Central Research Institute for Dryland Agriculture(Hyderabad)",
    "ICRISAT(Patancheru)"
  ],
  "contact_email": "Library-ICRISAT@cgiar.org",
  "eprintid": 421,
  "title": "Nutrient management strategies in participatory watersheds in semi arid tropical India",
  "creators": [
    {
      "name": {
        "family": "Rao",
        "given": "C S",
        "lineage": null,
        "honourific": null
      }
    },
    {
      "name": {
        "family": "Wani",
        "given": "S P",
        "lineage": null,
        "honourific": null
      }
    },
    {
      "name": {
        "family": "Sahrawat",
        "given": "K L",
        "lineage": null,
        "honourific": null
      }
    },
    {
      "name": {
        "family": "Rajasekharao",
        "given": "B",
        "lineage": null,
        "honourific": null
      }
    }
  ],
  "pagerange": "113-116",
  "publication": "Indian Journal of Fertilisers",
  "abstract": "Watershed based nutrient management options In different states (Andhra Pradesh, Madhya Pradesh, Karnataka, Rajasthan, Gujarat, Haryana and Tamil Nadu) were evaluated on farmer's fields based on initial soil characterization. Besides N and P, several other secondary and micronutrients such as S, Zn and B were found deficient in farmers' fields In watersheds. The extent of N deficiency In tested farmers' fields was 100%, P (upto 90%), Zn, B and S (upto 100%). Several ralnfed crops responded significantly to balanced application of nutrients to the extent of more than 100%. The cost benefit ratio In production of crops was higher when S, B andZn were supplied. Various integrated nutrient management options such as NP+mlcronutrients alongwith organic manures such as Gliricidia, vermicompost, tank silt, growing legumes in the systems or Rhizobium Inoculation, FYM or application of groundnut shells, etc showed the yield advantages. Integrated nutrient management (INM) along with soil and water conservation measures doubled the yields of several crops.",
  "status_changed": "2011-08-25 08:11:24",
  "full_text_status": "restricted",
  "related_url": [
    {
      "type": "author",
      "url": "http://scholar.google.co.in/scholar?as_q=Nutrient+management+strategies+in+participatory+watersheds+in+semi+arid+tropical+India&num=10&btnG=Search+Scholar&as_epq=&as_oq=&as_eq=&as_occt=title&as_sauthors=&as_publication=&as_ylo=&as_yhi=&as_sdt=1.&as_sdtp=o"
    }
  ],
  "item_issues_count": 0,
  "icrisatcreators": [
    {
      "name": {
        "family": "Wani",
        "given": "S P",
        "lineage": null,
        "honourific": null
      }
    },
    {
      "name": {
        "family": "Sahrawat",
        "given": "K L",
        "lineage": null,
        "honourific": null
      }
    },
    {
      "name": {
        "family": "Rajasekharao",
        "given": "B",
        "lineage": null,
        "honourific": null
      }
    }
  ],
  "refereed": "TRUE",
  "number": 12,
  "metadata_visibility": "show",
  "lastmod": "2011-08-25 08:11:43",
  "date": 2009,
  "eprint_status": "archive",
  "subjects": [
    "s2.14"
  ],
  "country": [
    "India"
  ],
  "documents": [
    {
      "pos": 1,
      "files": [
        {
          "objectid": 730,
          "fileid": 5133,
          "uri": "http://oar.icrisat.org/id/file/5133",
          "mtime": "2011-08-22 05:52:57",
          "hash_type": "MD5",
          "filename": "IndJouFert5_12_113-116_119-122_125-128_2009.pdf",
          "datasetid": "document",
          "filesize": 883422,
          "mime_type": "application/pdf",
          "hash": "1d762e5133df6dd9ca88669e1f483463"
        }
      ],
      "main": "IndJouFert5_12_113-116_119-122_125-128_2009.pdf",
      "uri": "http://oar.icrisat.org/id/document/730",
      "language": "en",
      "eprintid": 421,
      "docid": 730,
      "rev_number": 3,
      "placement": 1,
      "security": "validuser",
      "format": "application/pdf",
      "content": "published",
      "mime_type": "application/pdf"
    }
  ],
  "rev_number": 9,
  "dir": "disk0/00/00/04/21"
}