{
  "abstract": "Pigeonpea (Cajanus cajan L.) is an important food legume crop of rainfed agriculture. Owing to exposure of the crop to a number of biotic and abiotic stresses, the crop productivity has remained stagnant for almost last five decades at ca. 750 kg/ha. The availability of a cytoplasmic male sterility (CMS) system has facilitated the development and release of hybrids which are expected to enhance the productivity of pigeonpea. Recent advances in genomics and molecular breeding such as marker-assisted selection (MAS) offer the possibility to accelerate hybrid breeding. Molecular markers and genetic maps are pre-requisites for deploying MAS in breeding. However, in the case of pigeonpea, only one inter- and two intra-specific genetic maps are available so far. Here, four new intra-specific genetic maps comprising 59–140 simple sequence repeat (SSR) loci with map lengths ranging from 586.9 to 881.6 cM have been constructed. Using these four genetic maps together with two recently published intra-specific genetic maps, a consensus map was constructed, comprising of 339 SSR loci spanning a distance of 1,059 cM. Furthermore, quantitative trait loci (QTL) analysis for fertility restoration (Rf) conducted in three mapping populations identified four major QTLs explaining phenotypic variances up to 24 %. To the best of our knowledge, this is the first report on construction of a consensus genetic map in pigeonpea and on the identification of QTLs for fertility restoration. The developed consensus genetic map should serve as a reference for developing new genetic maps as well as correlating with the physical map in pigeonpea to be developed in near future. The availability of more informative markers in the bins harbouring QTLs for sterility mosaic disease (SMD) and Rf will facilitate the selection of the most suitable markers for genetic analysis and molecular breeding applications in pigeonpea. ",
  "eprint_status": "archive",
  "creators": [
    {
      "name": {
        "given": "A",
        "family": "Bohra",
        "lineage": null,
        "honourific": null
      }
    },
    {
      "name": {
        "given": "R K",
        "family": "Saxena",
        "lineage": null,
        "honourific": null
      }
    },
    {
      "name": {
        "given": "B N",
        "family": "Gnanesh",
        "lineage": null,
        "honourific": null
      }
    },
    {
      "name": {
        "given": "K B",
        "family": "Saxena",
        "lineage": null,
        "honourific": null
      }
    },
    {
      "name": {
        "given": "M",
        "family": "Byregowda",
        "lineage": null,
        "honourific": null
      }
    },
    {
      "name": {
        "given": "A",
        "family": "Rathore",
        "lineage": null,
        "honourific": null
      }
    },
    {
      "name": {
        "given": "P B",
        "family": "Kavi Kishor",
        "lineage": null,
        "honourific": null
      }
    },
    {
      "name": {
        "given": "D R",
        "family": "Cook",
        "lineage": null,
        "honourific": null
      }
    },
    {
      "name": {
        "given": "R K",
        "family": "Varshney",
        "lineage": null,
        "honourific": null
      }
    }
  ],
  "full_text_status": "public",
  "date_type": "published",
  "dir": "disk0/00/00/60/39",
  "rev_number": 18,
  "funders": [
    "Indian Council of Agricultural Research ",
    "Generation Challenge Programme"
  ],
  "number": 6,
  "issn": "1432-2242",
  "contact_email": "Library-ICRISAT@cgiar.org",
  "publication": "TAG Theoretical and Applied Genetics",
  "documents": [
    {
      "security": "public",
      "format": "application/pdf",
      "language": "en",
      "placement": 1,
      "mime_type": "application/pdf",
      "main": "TAG_125_ 6_1325-1338_2012.pdf",
      "uri": "http://oar.icrisat.org/id/document/24503",
      "docid": 24503,
      "files": [
        {
          "mtime": "2013-01-17 05:01:44",
          "hash": "0a5106eec259f7cb7f776209ae91e0bb",
          "objectid": 24503,
          "fileid": 88878,
          "datasetid": "document",
          "mime_type": "application/pdf",
          "uri": "http://oar.icrisat.org/id/file/88878",
          "filename": "TAG_125_ 6_1325-1338_2012.pdf",
          "hash_type": "MD5",
          "filesize": 1298765
        }
      ],
      "pos": 1,
      "eprintid": 6039,
      "rev_number": 1
    }
  ],
  "icrisatcreators": [
    {
      "name": {
        "given": "A",
        "family": "Bohra",
        "lineage": null,
        "honourific": null
      }
    },
    {
      "name": {
        "given": "K B",
        "family": "Saxena",
        "lineage": null,
        "honourific": null
      }
    },
    {
      "name": {
        "given": "B N",
        "family": "Gnanesh",
        "lineage": null,
        "honourific": null
      }
    },
    {
      "name": {
        "given": "K B",
        "family": "Saxena",
        "lineage": null,
        "honourific": null
      }
    },
    {
      "name": {
        "given": "A",
        "family": "Rathore",
        "lineage": null,
        "honourific": null
      }
    },
    {
      "name": {
        "given": "R K",
        "family": "Varshney",
        "lineage": null,
        "honourific": null
      }
    }
  ],
  "datestamp": "2012-07-12 04:40:05",
  "lastmod": "2018-05-08 07:59:42",
  "pagerange": "1325-1338",
  "metadata_visibility": "show",
  "userid": 30,
  "type": "article",
  "uri": "http://oar.icrisat.org/id/eprint/6039",
  "eprintid": 6039,
  "subjects": [
    "s1.2",
    "s2.13"
  ],
  "official_url": "http://dx.doi.org/10.1007/s00122-012-1916-5",
  "related_url": [
    {
      "url": "http://scholar.google.co.in/scholar?as_q=An+intra-specific+consensus+genetic+map+of+pigeonpea+%5BCajanus+cajan+%28L.%29+Millspaugh%5D+derived+from+six+mapping+populations+%22&as_epq=&as_oq=&as_eq=&as_occt=title&as_sauthors=&as_publication=&as_ylo=&as_yhi=",
      "type": "author"
    }
  ],
  "refereed": "TRUE",
  "affiliation": [
    "ICRISAT(Patancheru)",
    "Osmania University(Hyderabad)",
    "University of Agricultural Sciences(Bangalore)",
    "University of California(Davis)"
  ],
  "country": [
    "India",
    "USA"
  ],
  "publisher": "Springer Verlag",
  "ispublished": "pub",
  "date": 2012,
  "note": "The authors are thankful to Indian Council of Agricultural Research (ICAR) and Generation Challenge Programme (GCP) of CGIAR for supporting this research. Thanks are also due to Trushar Shah for his suggestions on CMap analysis, Naresh Kumar for generating some genotyping data for ICPB 2049 × ICPL 99050 population published in an earlier article and to Abdul Gafoor, S Ramesh and Ms. G Srivani for their excellent technical support.\r\nOpen Access   ",
  "volume": 125,
  "status_changed": "2012-07-12 04:40:05",
  "title": "An intra-specific consensus genetic map of pigeonpea [Cajanus cajan (L.) Millspaugh] derived from six mapping populations "
}