{
  "type": "monograph",
  "userid": 14,
  "publisher": "International Crops Research Institute for the Semi-Arid Tropics",
  "ispublished": "pub",
  "uri": "http://oar.icrisat.org/id/eprint/639",
  "datestamp": "2011-10-07 08:39:15",
  "affiliation": [
    "ICRISAT(Patancheru)"
  ],
  "contact_email": "Library-ICRISAT@cgiar.org",
  "eprintid": 639,
  "title": "An annotated bibliography of pigeonpea 1900-1977",
  "creators": [
    {
      "name": {
        "family": "Dahiya",
        "given": "B S",
        "lineage": null,
        "honourific": null
      }
    }
  ],
  "status_changed": "2011-10-07 08:39:15",
  "full_text_status": "public",
  "related_url": [
    {
      "type": "pub",
      "url": "http://scholar.google.co.in/scholar?hl=en&q=allintitle%3A+An+annotated+bibliography+of+pigeonpea+1900-1977&btnG=Search&as_sdt=0%2C5&as_ylo=&as_vis=0"
    }
  ],
  "item_issues_count": 0,
  "icrisatcreators": [
    {
      "name": {
        "family": "Dahiya",
        "given": "B S",
        "lineage": null,
        "honourific": null
      }
    }
  ],
  "metadata_visibility": "show",
  "lastmod": "2013-09-16 10:28:18",
  "date": 1980,
  "eprint_status": "archive",
  "subjects": [
    "s1.2"
  ],
  "country": [
    "India"
  ],
  "date_type": "published",
  "documents": [
    {
      "pos": 1,
      "files": [
        {
          "objectid": 950,
          "fileid": 7601,
          "uri": "http://oar.icrisat.org/id/file/7601",
          "mtime": "2011-08-29 11:32:23",
          "hash_type": "MD5",
          "filename": "RA_00014.pdf",
          "datasetid": "document",
          "filesize": 2762577,
          "mime_type": "application/pdf",
          "hash": "ed3c427e30c67c8d427992d00ea49b0e"
        }
      ],
      "main": "RA_00014.pdf",
      "uri": "http://oar.icrisat.org/id/document/950",
      "language": "en",
      "relation": [
        {
          "type": "http://eprints.org/relation/hasVolatileVersion",
          "uri": "/id/document/4652"
        },
        {
          "type": "http://eprints.org/relation/hasVersion",
          "uri": "/id/document/4652"
        },
        {
          "type": "http://eprints.org/relation/haspreviewThumbnailVersion",
          "uri": "/id/document/4652"
        },
        {
          "type": "http://eprints.org/relation/hasVolatileVersion",
          "uri": "/id/document/4653"
        },
        {
          "type": "http://eprints.org/relation/hasVersion",
          "uri": "/id/document/4653"
        },
        {
          "type": "http://eprints.org/relation/hasIndexCodesVersion",
          "uri": "/id/document/4653"
        }
      ],
      "eprintid": 639,
      "docid": 950,
      "rev_number": 4,
      "placement": 1,
      "security": "public",
      "format": "application/pdf",
      "mime_type": "application/pdf"
    }
  ],
  "pages": 196,
  "rev_number": 10,
  "institution": "International Crops Research Institute for the Semi-Arid Tropics",
  "monograph_type": "documentation",
  "dir": "disk0/00/00/06/39"
}