{
  "abstract": "Recurrent drought conditions that prevailed in the Sahel region of West Africa during the 1970s and 1980s have seriously challenged the resiliency of ecosystems and the adaptive capacity of human societies (IPCC 2001). This has triggered increased attention from the scientific community, resulting in a significant augmentation in climate-related publications and allowing for a better understanding of the complex regional and local climates",
  "eprint_status": "archive",
  "creators": [
    {
      "name": {
        "given": "P C S",
        "family": "Traore",
        "lineage": null,
        "honourific": null
      }
    },
    {
      "name": {
        "given": "M",
        "family": "Kouressy",
        "lineage": null,
        "honourific": null
      }
    },
    {
      "name": {
        "given": "M",
        "family": "Vaksmann",
        "lineage": null,
        "honourific": null
      }
    },
    {
      "name": {
        "given": "R",
        "family": "Tabo",
        "lineage": null,
        "honourific": null
      }
    },
    {
      "name": {
        "given": ".",
        "family": "et al",
        "lineage": null,
        "honourific": null
      }
    }
  ],
  "editors": [
    {
      "name": {
        "given": "M V K",
        "family": "Sivakumar",
        "lineage": null,
        "honourific": null
      }
    },
    {
      "name": {
        "given": "J",
        "family": "Hansen",
        "lineage": null,
        "honourific": null
      }
    }
  ],
  "full_text_status": "restricted",
  "date_type": "published",
  "dir": "disk0/00/00/70/24",
  "rev_number": 13,
  "book_title": "Climate Prediction and Agriculture",
  "pages": 306,
  "contact_email": "Library-ICRISAT@CGIAR.ORG",
  "documents": [
    {
      "content": "published",
      "security": "validuser",
      "format": "application/pdf",
      "language": "en",
      "placement": 1,
      "mime_type": "application/pdf",
      "main": "Climate Prediction and Agriculture_189-203_2007.pdf",
      "uri": "http://oar.icrisat.org/id/document/28872",
      "docid": 28872,
      "files": [
        {
          "mtime": "2013-08-01 10:10:41",
          "hash": "ae01db8b18160e339d53c7f28bf6a8ca",
          "objectid": 28872,
          "fileid": 99789,
          "datasetid": "document",
          "mime_type": "application/pdf",
          "uri": "http://oar.icrisat.org/id/file/99789",
          "filename": "Climate Prediction and Agriculture_189-203_2007.pdf",
          "hash_type": "MD5",
          "filesize": 364470
        }
      ],
      "pos": 1,
      "eprintid": 7024,
      "rev_number": 2
    }
  ],
  "icrisatcreators": [
    {
      "name": {
        "given": "P C S",
        "family": "Traore",
        "lineage": null,
        "honourific": null
      }
    },
    {
      "name": {
        "given": "R",
        "family": "Tabo",
        "lineage": null,
        "honourific": null
      }
    },
    {
      "name": {
        "given": ".",
        "family": "et al",
        "lineage": null,
        "honourific": null
      }
    }
  ],
  "datestamp": "2013-08-01 10:26:31",
  "lastmod": "2013-09-20 13:03:15",
  "pagerange": "189-203",
  "metadata_visibility": "show",
  "userid": 19,
  "type": "book_section",
  "place_of_pub": "New York",
  "uri": "http://oar.icrisat.org/id/eprint/7024",
  "eprintid": 7024,
  "series": "Advances and Challenges",
  "official_url": "http://dx.doi.org/10.1007/978-3-540-44650-7_19",
  "subjects": [
    "S1.5",
    "s1.4"
  ],
  "related_url": [
    {
      "url": "http://scholar.google.co.in/scholar?as_q=Climate+Prediction+and+Agriculture%3A+What+Is+Different+about+Sudano-Sahelian+West+Africa%3F&as_epq=&as_oq=&as_eq=&as_occt=title&as_sauthors=&as_publication=&as_ylo=&as_yhi=&btnG=&hl=en&as_sdt=0%2C5",
      "type": "pub"
    }
  ],
  "refereed": "TRUE",
  "isbn": "978-3-540-44649-1",
  "affiliation": [
    "ICRISAT(Bamako)",
    "Institut d’Economie Rurale(Bamako)",
    "Centre de Coopération Internationale en Recherche Agronomique pour le Développement(Bamako)",
    "ICRISAT(Niamey)"
  ],
  "country": [
    "Mali",
    "Niger"
  ],
  "publisher": "Springer Berlin Heidelberg",
  "ispublished": "pub",
  "date": 2007,
  "volume": 26,
  "status_changed": "2013-08-01 10:26:31",
  "title": "Climate prediction and agriculture: What Is different about Sudano-Sahelian West Africa?"
}